pynavi/__init__.py
pynavi/common.py
pynavi/exceptions.py
pynavi/middleware.py
pynavi/types.py
pynavi/clients/__init__.py
pynavi/clients/apollo.py
pynavi/clients/oss.py
pynavi/clients/sentry.py
pynavi/component/__init__.py
pynavi/engine/__init__.py
pynavi/engine/locks.py
pynavi/engine/cache/__init__.py
pynavi/engine/cache/memcached.py
pynavi/engine/cache/rediscache.py
pynavi/engine/pattern/__init__.py
pynavi/engine/pattern/chain.py
pynavi/engine/pattern/observer.py
pynavi/engine/pattern/singleton.py
pynavi/engine/pattern/strategy.py
pynavi/engine/protocol/__init__.py
pynavi/model/__init__.py
pynavi/service/__init__.py
pynavi/service/http.py
pynavi/service/https.py
pynavi/service/rpc.py
pynavi/util/__init__.py
pynavi/util/string.py
pynavi/view/__init__.py
pynavi/view/views.py
pynavi/view/reqponse/__init__.py
pynavi/view/request/__init__.py
pynavi/view/request/url_refactor.py
pynavi-0.1.2.dist-info/METADATA
pynavi-0.1.2.dist-info/RECORD
pynavi-0.1.2.dist-info/WHEEL
pynavi-0.1.2.dist-info/top_level.txt
